af2plots/__main__.py
af2plots/plotter.py
af2plots/version.py
examples/PIAQ_test_af2mmer_dimer/input/features.pkl
examples/PIAQ_test_af2mmer_dimer/input/ranked_0.pdb
examples/PIAQ_test_af2mmer_dimer/input/ranked_1.pdb
examples/PIAQ_test_af2mmer_dimer/input/ranked_2.pdb
examples/PIAQ_test_af2mmer_dimer/input/ranked_3.pdb
examples/PIAQ_test_af2mmer_dimer/input/ranked_4.pdb
examples/PIAQ_test_af2mmer_dimer/input/ranking_debug.json
examples/PIAQ_test_af2mmer_dimer/input/relaxed_model_1_multimer.pdb
examples/PIAQ_test_af2mmer_dimer/input/relaxed_model_2_multimer.pdb
examples/PIAQ_test_af2mmer_dimer/input/relaxed_model_3_multimer.pdb
examples/PIAQ_test_af2mmer_dimer/input/relaxed_model_4_multimer.pdb
examples/PIAQ_test_af2mmer_dimer/input/relaxed_model_5_multimer.pdb
examples/PIAQ_test_af2mmer_dimer/input/result_model_1_multimer.pkl
examples/PIAQ_test_af2mmer_dimer/input/result_model_2_multimer.pkl
examples/PIAQ_test_af2mmer_dimer/input/result_model_3_multimer.pkl
examples/PIAQ_test_af2mmer_dimer/input/result_model_4_multimer.pkl
examples/PIAQ_test_af2mmer_dimer/input/result_model_5_multimer.pkl
examples/PIAQ_test_af2mmer_dimer/input/timings.json
examples/PIAQ_test_af2mmer_dimer/input/unrelaxed_model_1_multimer.pdb
examples/PIAQ_test_af2mmer_dimer/input/unrelaxed_model_2_multimer.pdb
examples/PIAQ_test_af2mmer_dimer/input/unrelaxed_model_3_multimer.pdb
examples/PIAQ_test_af2mmer_dimer/input/unrelaxed_model_4_multimer.pdb
examples/PIAQ_test_af2mmer_dimer/input/unrelaxed_model_5_multimer.pdb
examples/PIAQ_test_af2mmer_dimer/input/msas/A/bfd_uniclust_hits.a3m
examples/PIAQ_test_af2mmer_dimer/input/msas/A/mgnify_hits.sto
examples/PIAQ_test_af2mmer_dimer/input/msas/A/pdb_hits.sto
examples/PIAQ_test_af2mmer_dimer/input/msas/A/uniref90_hits.sto
af2plots-0.1.5.dist-info/METADATA
af2plots-0.1.5.dist-info/WHEEL
af2plots-0.1.5.dist-info/entry_points.txt
af2plots-0.1.5.dist-info/top_level.txt
af2plots-0.1.5.dist-info/RECORD
