Metadata-Version: 2.4
Name: af2plots
Version: 0.1.5
Summary: AF2 plots plots
Home-page: https://git.embl.de/gchojnowski/af2plots
Author: Grzegorz Chojnowski
Author-email: gchojnowski@embl-hamburg.de
Dynamic: author
Dynamic: author-email
Dynamic: home-page
Dynamic: summary
